pyline/__init__.py
pyline/command.py
pyline/handler_mediator.py
pyline/pipe.py
pyline/query.py
pyline_core-0.1.dist-info/licenses/LICENSE
pyline_core-0.1.dist-info/METADATA
pyline_core-0.1.dist-info/WHEEL
pyline_core-0.1.dist-info/top_level.txt
pyline_core-0.1.dist-info/RECORD
