Metadata-Version: 2.4
Name: pyline-core
Version: 0.1
Summary: pyline core
Author: Alp Sakaci
Author-email: alp@alpsakaci.com
Requires-Python: >=3.10
License-File: LICENSE
Dynamic: author
Dynamic: author-email
Dynamic: description
Dynamic: description-content-type
Dynamic: license-file
Dynamic: requires-python
Dynamic: summary
